pyTEMlib/__init__.py
pyTEMlib/animation.py
pyTEMlib/atom_tools.py
pyTEMlib/config_dir.py
pyTEMlib/core_loss_widget.py
pyTEMlib/crystal_tools.py
pyTEMlib/diffraction_plot.py
pyTEMlib/dynamic_scattering.py
pyTEMlib/eds_tools.py
pyTEMlib/eels_dialog.py
pyTEMlib/eels_dialog_utilities.py
pyTEMlib/eels_tools.py
pyTEMlib/file_tools.py
pyTEMlib/file_tools_qt.py
pyTEMlib/graph_tools.py
pyTEMlib/graph_viz.py
pyTEMlib/image_dialog.py
pyTEMlib/image_dlg.py
pyTEMlib/image_tools.py
pyTEMlib/info_widget.py
pyTEMlib/info_widget3.py
pyTEMlib/interactive_image.py
pyTEMlib/kinematic_scattering.py
pyTEMlib/low_loss_widget.py
pyTEMlib/microscope.py
pyTEMlib/peak_dialog.py
pyTEMlib/peak_dlg.py
pyTEMlib/probe_tools.py
pyTEMlib/sidpy_tools.py
pyTEMlib/simulation_tools.py
pyTEMlib/version.py
pyTEMlib/xrpa_x_sections.py
pycrosGUI-0.2025.2.0.dist-info/LICENSE
pycrosGUI-0.2025.2.0.dist-info/METADATA
pycrosGUI-0.2025.2.0.dist-info/WHEEL
pycrosGUI-0.2025.2.0.dist-info/entry_points.txt
pycrosGUI-0.2025.2.0.dist-info/top_level.txt
pycrosGUI-0.2025.2.0.dist-info/RECORD
