Metadata-Version: 2.2
Name: pycrosGUI
Version: 0.2025.2.0
Summary: pyTEM: TEM Data Quantification library through a model-based approach
Home-page: https://pycroscopy.github.io/pycrosGUI/about.html
Author: Gerd Duscher
Author-email: gduscher@utk.edu
License: MIT
Keywords: imaging,spectra,transmission,electron,microscopy,scientific,scanning,eels,visualization,processing,storage,hdf5,diffraction
Platform: Linux
Platform: Mac OSX
Platform: Windows 11/10
Classifier: Development Status :: 2 - Pre-Alpha
Classifier: Environment :: Console
Classifier: Intended Audience :: Science/Research
Classifier: License :: OSI Approved :: MIT License
Classifier: Natural Language :: English
Classifier: Operating System :: OS Independent
Classifier: Programming Language :: Cython
Classifier: Programming Language :: Python :: 3
Classifier: Programming Language :: Python :: 3.10
Classifier: Programming Language :: Python :: 3.11
Classifier: Programming Language :: Python :: 3.12
Classifier: Programming Language :: Python :: Implementation :: CPython
Classifier: Topic :: Scientific/Engineering :: Information Analysis
License-File: LICENSE
Requires-Dist: pyTEMlib
Requires-Dist: pyqt5
Requires-Dist: pyqtgraph
Dynamic: author
Dynamic: author-email
Dynamic: classifier
Dynamic: description
Dynamic: home-page
Dynamic: keywords
Dynamic: license
Dynamic: platform
Dynamic: requires-dist
Dynamic: summary
